<DsRadarCalib>
  <radarName>DOW6</radarName>
  <calibTime>2013-11-26T17:29:21</calibTime>
  <wavelengthCm>3.18928</wavelengthCm>
  <beamWidthDegH>1</beamWidthDegH>
  <beamWidthDegV>1</beamWidthDegV>
  <antGainDbH>44.3</antGainDbH>
  <antGainDbV>44.3</antGainDbV>
  <pulseWidthUs>0.5</pulseWidthUs>
  <xmitPowerDbmH>77.3</xmitPowerDbmH>
  <xmitPowerDbmV>77.3</xmitPowerDbmV>
  <twoWayWaveguideLossDbH>2</twoWayWaveguideLossDbH>
  <twoWayWaveguideLossDbV>2</twoWayWaveguideLossDbV>
  <twoWayRadomeLossDbH>0</twoWayRadomeLossDbH>
  <twoWayRadomeLossDbV>0</twoWayRadomeLossDbV>
  <receiverMismatchLossDb>1.3</receiverMismatchLossDb>
  <kSquaredWater>0.93</kSquaredWater>
  <radarConstH>74.7903</radarConstH>
  <radarConstV>74.7903</radarConstV>
  <noiseDbmHc>-53.9089</noiseDbmHc>
  <noiseDbmHx>-53.9089</noiseDbmHx>
  <noiseDbmVc>-56.353</noiseDbmVc>
  <noiseDbmVx>-56.353</noiseDbmVx>
  <i0DbmHc>-107.93</i0DbmHc>
  <i0DbmHx>-107.93</i0DbmHx>
  <i0DbmVc>-108.749</i0DbmVc>
  <i0DbmVx>-108.749</i0DbmVx>
  <receiverGainDbHc>54.0207</receiverGainDbHc>
  <receiverGainDbHx>54.0207</receiverGainDbHx>
  <receiverGainDbVc>52.3956</receiverGainDbVc>
  <receiverGainDbVx>52.3956</receiverGainDbVx>
  <receiverSlopeDbHc>1.01026</receiverSlopeDbHc>
  <receiverSlopeDbHx>1.01026</receiverSlopeDbHx>
  <receiverSlopeDbVc>1.02948</receiverSlopeDbVc>
  <receiverSlopeDbVx>1.02948</receiverSlopeDbVx>
  <dynamicRangeDbHc>65.7596</dynamicRangeDbHc>
  <dynamicRangeDbHx>65.7596</dynamicRangeDbHx>
  <dynamicRangeDbVc>68.3542</dynamicRangeDbVc>
  <dynamicRangeDbVx>68.3542</dynamicRangeDbVx>
  <baseDbz1kmHc>-33.1377</baseDbz1kmHc>
  <baseDbz1kmHx>-33.1377</baseDbz1kmHx>
  <baseDbz1kmVc>-33.9448</baseDbz1kmVc>
  <baseDbz1kmVx>-33.9448</baseDbz1kmVx>
  <sunPowerDbmHc>-9999</sunPowerDbmHc>
  <sunPowerDbmHx>-9999</sunPowerDbmHx>
  <sunPowerDbmVc>-9999</sunPowerDbmVc>
  <sunPowerDbmVx>-9999</sunPowerDbmVx>
  <noiseSourcePowerDbmH>-9999</noiseSourcePowerDbmH>
  <noiseSourcePowerDbmV>-9999</noiseSourcePowerDbmV>
  <powerMeasLossDbH>0</powerMeasLossDbH>
  <powerMeasLossDbV>0</powerMeasLossDbV>
  <couplerForwardLossDbH>27.04</couplerForwardLossDbH>
  <couplerForwardLossDbV>27.13</couplerForwardLossDbV>
  <zdrCorrectionDb>0</zdrCorrectionDb>
  <ldrCorrectionDbH>0</ldrCorrectionDbH>
  <ldrCorrectionDbV>0</ldrCorrectionDbV>
  <systemPhidpDeg>-70</systemPhidpDeg>
  <testPowerDbmH>-9999</testPowerDbmH>
  <testPowerDbmV>-9999</testPowerDbmV>
</DsRadarCalib>
